[
  {"registrationNo":101,"name":"井上拓海","branch":"浜名湖","className":"A1","age":29,"nationalWin":6.8,"localWin":7.1,"national2Win":3.2,"local2Win":3.5,"avgSt":0.14,"motorRate":41,"boatRate":39,"exhibitionTime":6.72,"weight":53,"tilt":2,"currentForm":"6-4-2"},
  {"registrationNo":102,"name":"宮川隼人","branch":"浜名湖","className":"A1","age":31,"nationalWin":6.4,"localWin":6.7,"national2Win":3.0,"local2Win":3.2,"avgSt":0.15,"motorRate":37,"boatRate":35,"exhibitionTime":6.78,"weight":54,"tilt":1,"currentForm":"5-3-1"},
  {"registrationNo":103,"name":"藤田誠","branch":"愛知","className":"A2","age":34,"nationalWin":6.1,"localWin":6.3,"national2Win":2.8,"local2Win":3.0,"avgSt":0.16,"motorRate":33,"boatRate":32,"exhibitionTime":6.86,"weight":55,"tilt":0,"currentForm":"4-5-3"},
  {"registrationNo":104,"name":"山内亮","branch":"静岡","className":"A2","age":27,"nationalWin":5.9,"localWin":6.1,"national2Win":2.7,"local2Win":2.9,"avgSt":0.17,"motorRate":31,"boatRate":30,"exhibitionTime":6.91,"weight":56,"tilt":-1,"currentForm":"3-4-5"},
  {"registrationNo":105,"name":"佐々木翔","branch":"岐阜","className":"B1","age":36,"nationalWin":5.6,"localWin":5.9,"national2Win":2.4,"local2Win":2.6,"avgSt":0.18,"motorRate":29,"boatRate":28,"exhibitionTime":6.95,"weight":57,"tilt":-2,"currentForm":"2-6-4"},
  {"registrationNo":106,"name":"渡辺大地","branch":"三重","className":"B1","age":33,"nationalWin":5.3,"localWin":5.5,"national2Win":2.2,"local2Win":2.4,"avgSt":0.19,"motorRate":27,"boatRate":26,"exhibitionTime":7.02,"weight":58,"tilt":-3,"currentForm":"1-5-6"},
  {"registrationNo":107,"name":"小林直人","branch":"蒲郡","className":"A1","age":30,"nationalWin":6.9,"localWin":7.2,"national2Win":3.3,"local2Win":3.6,"avgSt":0.13,"motorRate":42,"boatRate":40,"exhibitionTime":6.68,"weight":52,"tilt":3,"currentForm":"7-3-1"},
  {"registrationNo":108,"name":"高橋優","branch":"愛知","className":"A1","age":28,"nationalWin":6.6,"localWin":6.9,"national2Win":3.1,"local2Win":3.3,"avgSt":0.14,"motorRate":38,"boatRate":36,"exhibitionTime":6.74,"weight":53,"tilt":1,"currentForm":"6-2-2"},
  {"registrationNo":109,"name":"石川大","branch":"静岡","className":"A2","age":32,"nationalWin":6.3,"localWin":6.5,"national2Win":2.9,"local2Win":3.1,"avgSt":0.15,"motorRate":34,"boatRate":33,"exhibitionTime":6.81,"weight":54,"tilt":0,"currentForm":"4-4-4"},
  {"registrationNo":110,"name":"中村航","branch":"岐阜","className":"A2","age":26,"nationalWin":6.0,"localWin":6.2,"national2Win":2.7,"local2Win":2.9,"avgSt":0.16,"motorRate":32,"boatRate":31,"exhibitionTime":6.88,"weight":55,"tilt":-1,"currentForm":"3-5-5"},
  {"registrationNo":111,"name":"加藤慎","branch":"三重","className":"B1","age":35,"nationalWin":5.8,"localWin":6.0,"national2Win":2.5,"local2Win":2.7,"avgSt":0.17,"motorRate":30,"boatRate":29,"exhibitionTime":6.93,"weight":56,"tilt":-2,"currentForm":"2-4-6"},
  {"registrationNo":112,"name":"森田裕","branch":"兵庫","className":"B1","age":34,"nationalWin":5.4,"localWin":5.7,"national2Win":2.3,"local2Win":2.5,"avgSt":0.18,"motorRate":28,"boatRate":27,"exhibitionTime":7.00,"weight":57,"tilt":-3,"currentForm":"1-6-5"},
  {"registrationNo":113,"name":"田中健太","branch":"浜名湖","className":"A1","age":30,"nationalWin":6.7,"localWin":7.0,"national2Win":3.1,"local2Win":3.4,"avgSt":0.14,"motorRate":39,"boatRate":37,"exhibitionTime":6.74,"weight":53,"tilt":2,"currentForm":"5-4-2"},
  {"registrationNo":114,"name":"松本将","branch":"愛知","className":"A1","age":29,"nationalWin":6.5,"localWin":6.8,"national2Win":2.9,"local2Win":3.2,"avgSt":0.15,"motorRate":35,"boatRate":34,"exhibitionTime":6.79,"weight":54,"tilt":1,"currentForm":"4-3-3"},
  {"registrationNo":115,"name":"伊藤悠","branch":"静岡","className":"A2","age":33,"nationalWin":6.2,"localWin":6.4,"national2Win":2.8,"local2Win":3.0,"avgSt":0.16,"motorRate":33,"boatRate":32,"exhibitionTime":6.85,"weight":55,"tilt":0,"currentForm":"4-5-2"},
  {"registrationNo":116,"name":"吉田和也","branch":"岐阜","className":"A2","age":27,"nationalWin":6.0,"localWin":6.2,"national2Win":2.6,"local2Win":2.8,"avgSt":0.16,"motorRate":31,"boatRate":30,"exhibitionTime":6.90,"weight":56,"tilt":-1,"currentForm":"3-6-4"},
  {"registrationNo":117,"name":"木村仁","branch":"三重","className":"B1","age":35,"nationalWin":5.7,"localWin":6.0,"national2Win":2.5,"local2Win":2.7,"avgSt":0.17,"motorRate":29,"boatRate":28,"exhibitionTime":6.96,"weight":57,"tilt":-2,"currentForm":"2-5-6"},
  {"registrationNo":118,"name":"池田俊","branch":"兵庫","className":"B1","age":34,"nationalWin":5.3,"localWin":5.6,"national2Win":2.2,"local2Win":2.4,"avgSt":0.18,"motorRate":27,"boatRate":26,"exhibitionTime":7.03,"weight":58,"tilt":-3,"currentForm":"1-4-5"},
  {"registrationNo":119,"name":"今野陽斗","branch":"浜名湖","className":"A1","age":31,"nationalWin":6.6,"localWin":6.9,"national2Win":3.0,"local2Win":3.3,"avgSt":0.15,"motorRate":38,"boatRate":36,"exhibitionTime":6.77,"weight":54,"tilt":1,"currentForm":"5-2-3"},
  {"registrationNo":120,"name":"岸本真","branch":"愛知","className":"A1","age":28,"nationalWin":6.4,"localWin":6.7,"national2Win":2.9,"local2Win":3.1,"avgSt":0.15,"motorRate":35,"boatRate":34,"exhibitionTime":6.82,"weight":54,"tilt":0,"currentForm":"4-4-4"},
  {"registrationNo":121,"name":"平野剛","branch":"静岡","className":"A2","age":32,"nationalWin":6.1,"localWin":6.3,"national2Win":2.7,"local2Win":2.9,"avgSt":0.16,"motorRate":33,"boatRate":32,"exhibitionTime":6.87,"weight":55,"tilt":0,"currentForm":"4-3-5"},
  {"registrationNo":122,"name":"武田哲","branch":"岐阜","className":"A2","age":29,"nationalWin":5.9,"localWin":6.1,"national2Win":2.6,"local2Win":2.8,"avgSt":0.17,"motorRate":31,"boatRate":30,"exhibitionTime":6.92,"weight":56,"tilt":-1,"currentForm":"3-5-4"},
  {"registrationNo":123,"name":"福田翔","branch":"三重","className":"B1","age":36,"nationalWin":5.7,"localWin":5.9,"national2Win":2.4,"local2Win":2.6,"avgSt":0.18,"motorRate":29,"boatRate":28,"exhibitionTime":6.97,"weight":57,"tilt":-2,"currentForm":"2-4-6"},
  {"registrationNo":124,"name":"原田勝","branch":"兵庫","className":"B1","age":33,"nationalWin":5.4,"localWin":5.6,"national2Win":2.2,"local2Win":2.4,"avgSt":0.19,"motorRate":27,"boatRate":26,"exhibitionTime":7.04,"weight":58,"tilt":-3,"currentForm":"1-5-5"},
  {"registrationNo":125,"name":"青木誠","branch":"浜名湖","className":"A1","age":30,"nationalWin":6.5,"localWin":6.8,"national2Win":3.0,"local2Win":3.2,"avgSt":0.14,"motorRate":37,"boatRate":35,"exhibitionTime":6.75,"weight":53,"tilt":2,"currentForm":"5-3-2"},
  {"registrationNo":126,"name":"大島優","branch":"愛知","className":"A1","age":27,"nationalWin":6.3,"localWin":6.6,"national2Win":2.8,"local2Win":3.0,"avgSt":0.15,"motorRate":35,"boatRate":34,"exhibitionTime":6.80,"weight":54,"tilt":1,"currentForm":"4-2-4"},
  {"registrationNo":127,"name":"辻本拓","branch":"静岡","className":"A2","age":32,"nationalWin":6.0,"localWin":6.2,"national2Win":2.6,"local2Win":2.8,"avgSt":0.16,"motorRate":32,"boatRate":31,"exhibitionTime":"6.84","weight":55,"tilt":0,"currentForm":"3-4-5"},
  {"registrationNo":128,"name":"長谷川誠","branch":"岐阜","className":"A2","age":30,"nationalWin":5.8,"localWin":6.0,"national2Win":2.5,"local2Win":2.7,"avgSt":0.17,"motorRate":31,"boatRate":30,"exhibitionTime":6.90,"weight":56,"tilt":-1,"currentForm":"3-5-3"},
  {"registrationNo":129,"name":"本田健","branch":"三重","className":"B1","age":35,"nationalWin":5.6,"localWin":5.8,"national2Win":2.3,"local2Win":2.5,"avgSt":0.18,"motorRate":29,"boatRate":28,"exhibitionTime":6.96,"weight":57,"tilt":-2,"currentForm":"2-4-6"},
  {"registrationNo":130,"name":"近藤秀","branch":"兵庫","className":"B1","age":34,"nationalWin":5.2,"localWin":5.4,"national2Win":2.1,"local2Win":2.3,"avgSt":0.19,"motorRate":27,"boatRate":26,"exhibitionTime":7.02,"weight":58,"tilt":-3,"currentForm":"1-5-5"}
]
